creategif/__init__.py
creategif/animator.py
creategif-0.0.1.dist-info/LICENSE.md
creategif-0.0.1.dist-info/METADATA
creategif-0.0.1.dist-info/WHEEL
creategif-0.0.1.dist-info/top_level.txt
creategif-0.0.1.dist-info/RECORD
